{
  "type": "Feature",
  "geometry": {
    "type": "Polygon",
    "coordinates": [[
      [10.2034, 56.1568],
      [10.2082, 56.1542],
      [10.2072, 56.1504],
      [10.2034, 56.1492],
      [10.1992, 56.1510],
      [10.1998, 56.1550],
      [10.2034, 56.1568]
    ]]
  },
  "properties": {
    "id": "2",
    "name": "Aarhus Nord Hundeskov",
    "address": "Viby, Aarhus Kommune",
    "size_hectares": 6.8,
    "feature_keys": ["fenced", "parking", "water", "benches", "small_dogs", "accessible"],
    "description": "Stor hundeskov med både skov og åbent græsareal. Populær i weekenden."
  }
}
